LICENSE
README.md
pyproject.toml
setup.py
nse_fno_expiry_calculator/__init__.py
nse_fno_expiry_calculator/util.py
nse_fno_expiry_calculator.egg-info/PKG-INFO
nse_fno_expiry_calculator.egg-info/SOURCES.txt
nse_fno_expiry_calculator.egg-info/dependency_links.txt
nse_fno_expiry_calculator.egg-info/requires.txt
nse_fno_expiry_calculator.egg-info/top_level.txt