Metadata-Version: 2.1
Name: nse-fno-expiry-calculator
Version: 1.0.0
Summary: Util to calculate expiry date for FNO instruments which also considers NSE holiday calendar.
Home-page: https://github.com/rakesh1988/nse-fno-expiry-calculator.git
Author: Rakesh Ravikumar Kashyap
Author-email: rakesh1988@gmail.com
License: UNKNOWN
Keywords: nse,expiry,nse fno,nse holiday,trading,stock markets
Platform: UNKNOWN
Classifier: Intended Audience :: Developers
Classifier: Natural Language :: English
Classifier: Operating System :: OS Independent
Classifier: Programming Language :: Python
Classifier: Programming Language :: Python :: 3.6
Classifier: Programming Language :: Python :: Implementation :: PyPy
Classifier: Topic :: Software Development :: Libraries :: Python Modules
Requires-Python: >=3.6
